prev_gen/__init__.py
prev_gen/color.py
prev_gen/config.py
prev_gen/distance.py
prev_gen/example.txt
prev_gen/nunito.ttf
prev_gen/palette.py
prev_gen/previewer.py
prev_gen/reverser.py
prev_gen/script.py
prev_gen/settings.py
prev_gen/tile.py
prev_gen/types.py
prev_gen-7.0.0.dist-info/LICENSE
prev_gen-7.0.0.dist-info/METADATA
prev_gen-7.0.0.dist-info/WHEEL
prev_gen-7.0.0.dist-info/entry_points.txt
prev_gen-7.0.0.dist-info/top_level.txt
prev_gen-7.0.0.dist-info/RECORD
