Metadata-Version: 2.2
Name: prev_gen
Version: 7.0.0
Summary: Palette preview generator
Author-email: Remigiusz Dończyk <donczyk.remigiusz@gmail.com>
License:                     GNU GENERAL PUBLIC LICENSE
Project-URL: Documentation, https://github.com/Aonodensetsu/prev_gen/blob/main/WIKI.md
Project-URL: Repository, https://github.com/Aonodensetsu/prev_gen
Project-URL: Changelog, https://github.com/Aonodensetsu/prev_gen/blob/main/CHANGELOG.md
Keywords: palette,preview,generator,image,color,graphics
Classifier: Development Status :: 6 - Mature
Classifier: Environment :: Console
Classifier: Intended Audience :: Developers
Classifier: License :: OSI Approved :: GNU General Public License v3 (GPLv3)
Classifier: Natural Language :: English
Classifier: Operating System :: OS Independent
Classifier: Programming Language :: Python :: 3.10
Classifier: Topic :: Artistic Software
Classifier: Topic :: Multimedia :: Graphics :: Graphics Conversion
Classifier: Topic :: Multimedia :: Graphics :: Presentation
Classifier: Topic :: Software Development :: Libraries :: Python Modules
Classifier: Typing :: Typed
Requires-Python: >=3.10
License-File: LICENSE
Requires-Dist: colour-science>=0.4.5
Requires-Dist: drawsvg<3
Requires-Dist: matplotlib
Requires-Dist: multimethod
Requires-Dist: networkx
Requires-Dist: pillow
Requires-Dist: pyyaml
Requires-Dist: tomlkit
Requires-Dist: tqdm
